contNb.vhd
library IEEE;
use IEEE.std_logic_1164.all;
use IEEE.numeric_std.all;

entity contNb is
    generic(N:natural :=4);
	port(
		clk_i: in std_logic;
		rst_i: in std_logic;
		ena_i: in std_logic;
        asc_i: in std_logic;
		q: out std_logic_vector(N-1 downto 0)
	);
end;

architecture contNb_arq of contNb is
    signal aux: unsigned(N-1 downto 0);
begin

    process(clk_i)
    
    begin
        if rising_edge(clk_i) then
            if rst_i = '1' then
                aux <= (others => '0');
                --count <= (others => '0');
            elsif ena_i = '1' then
                if asc_i = '1' then
                    aux <= aux + 1;
                    --count <= count + '1';
                else
                    aux <= aux - 1;
                    --count <= count - '1';
                end if;
            end if;
        end if;
        --q <= count;
        q <= std_logic_vector(aux);
    end process;

    
            
end;

contNb_ctl.vhd
-----------------------------------------------------------------------------
--  
--  
--
--  Project  : UART controlled counter
--  Module   : contNb_ctl.v
--  Parent   : uart_cont.v
--  Children : None
--
--  Description: 
--     Counter output generator
--
--  Parameters:
--     None
--
--  Local Parameters:
--
--  Notes       : 
--
--  Multicycle and False Paths
--    None
--

library IEEE;
use IEEE.std_logic_1164.all;

entity contNb_ctl is
	generic(N:natural :=4);
	port(
		clk_i:			in std_logic;						-- Clock input
		ena_i:          in std_logic;                       -- External enable
		rx_data:		in std_logic_vector(7 downto 0);	-- 8 bit data input
		rx_data_rdy:	in std_logic;						-- valid when rx_data_rdy is asserted
		count_o:		out std_logic_vector(N-1 downto 0)	-- The counter outputs
	);
end;


architecture contNb_ctl_arq of contNb_ctl is

	component contNb is
		generic(N:natural :=4);
		port(
			clk_i: in std_logic;
			rst_i: in std_logic;
			ena_i: in std_logic;
			asc_i: in std_logic;
			q: out std_logic_vector(N-1 downto 0)
		);
	end component;

	signal old_rx_data_rdy: std_logic;
	signal rst,asc,ena: std_logic;
	signal aux: std_logic := '0';

begin

	contNb_i0: contNb
		generic map(N => N)
		port map(
			clk_i => clk_i,
			rst_i => rst,
			ena_i => ena,
			asc_i => asc,
			q 	  => count_o
		);

	process(clk_i)
	begin
		if rising_edge(clk_i) then
			if rst = '1' then
				old_rx_data_rdy <= '0';
				rst <= '0';
			else
				-- Capture the value of rx_data_rdy for edge detection
				old_rx_data_rdy <= rx_data_rdy;
				-- If rising edge of rx_data_rdy, capture rx_data
				if (rx_data_rdy = '1' and old_rx_data_rdy = '0') then
					rst <= rx_data(0);
					aux <= rx_data(1);
					asc <= rx_data(2);
				end if;
			end if;	-- if !rst
		end if;
	end process;
	
    ena <= aux and ena_i;
end;

contNb_ctl_tb.vhd
library IEEE;
use IEEE.std_logic_1164.all;
use IEEE.numeric_std.all;

entity contNb_ctl_tb is
end;

architecture contNb_ctl_tb_arq of contNb_ctl_tb is

    component contNb_ctl is
        generic(N:natural :=4);
        port(
            clk_i:			in std_logic;
			ena_i:          in std_logic;   						-- Clock input
            rx_data:		in std_logic_vector(7 downto 0);	-- 8 bit data input
            rx_data_rdy:	in std_logic;						-- valid when rx_data_rdy is asserted
            count_o:		out std_logic_vector(N-1 downto 0)	-- The counter outputs
        );
    end component;

	constant N_used: integer :=4;
	constant half_period: time := 1 ps;--10 ns;

    signal ena: std_logic := '1';
	signal clock : std_logic := '1';
	signal cont_out: std_logic_vector(N_used-1 downto 0);
    signal data_rdy: std_logic := '0';
    signal data: std_logic_vector(7 downto 0);
	
begin

	DUT: contNb_ctl
		generic map(N => N_used)
		port map(
			clk_i => clock,
			ena_i => ena,
			rx_data => data,
			rx_data_rdy => data_rdy,
			count_o  => cont_out
		);
	

	clk_process :process
	begin
		clock <= '0';
		wait for half_period;  --for half of clock period clk stays at '0'.
		clock <= '1';
		wait for half_period;  --for next half of clock period clk stays at '1'.
	end process;
	
	stim_proc: process
	begin        
		wait for half_period*2*5; --wait for 5 clock cycles.
       	data <= "00000001"; -- asc=0 ena=0 rst=1
        wait for half_period*2*2; --wait for 2 clock cycles.
      	data_rdy <= '1';
        wait for half_period*2*1; --wait for 1 clock cycles.
        data_rdy <= '0';

		wait for half_period*2*10; --wait for 10 clock cycles.
		data <= "00000010"; -- asc=0 ena=1 rst=0
        wait for half_period*2*2; --wait for 2 clock cycles.
        data_rdy <= '1';
        wait for half_period*2*1; --wait for 1 clock cycles.
        data_rdy <= '0';

		wait for half_period*2*40; --wait for 40 clock cycles.
		data <= "00000011"; -- asc=0 ena=1 rst=1
        wait for half_period*2*2; --wait for 2 clock cycles.
        data_rdy <= '1';
        wait for half_period*2*1; --wait for 1 clock cycles.
        data_rdy <= '0';
		wait for half_period*2*40; --wait for 40 clock cycles.

		wait for half_period*2*40; --wait for 40 clock cycles.
		data <= "00000100"; -- asc=1 ena=0 rst=0
        wait for half_period*2*2; --wait for 2 clock cycles.
        data_rdy <= '1';
        wait for half_period*2*1; --wait for 1 clock cycles.
        data_rdy <= '0';
		wait for half_period*2*40; --wait for 40 clock cycles.

		wait for half_period*2*40; --wait for 40 clock cycles.
		data <= "00000101"; -- asc=1 ena=0 rst=1
        wait for half_period*2*2; --wait for 2 clock cycles.
        data_rdy <= '1';
        wait for half_period*2*1; --wait for 1 clock cycles.
        data_rdy <= '0';
		wait for half_period*2*40; --wait for 40 clock cycles.

		wait for half_period*2*40; --wait for 40 clock cycles.
		data <= "00000110"; -- asc=1 ena=1 rst=0
        wait for half_period*2*2; --wait for 2 clock cycles.
        data_rdy <= '1';
        wait for half_period*2*1; --wait for 1 clock cycles.
        data_rdy <= '0';
		wait for half_period*2*40; --wait for 40 clock cycles.

		wait for half_period*2*40; --wait for 40 clock cycles.
		data <= "00000111"; -- asc=1 ena=1 rst=1
        wait for half_period*2*2; --wait for 2 clock cycles.
        data_rdy <= '1';
        wait for half_period*2*1; --wait for 1 clock cycles.
        data_rdy <= '0';
		wait for half_period*2*40; --wait for 40 clock cycles.
		assert false report "Test: OK" severity failure;
   end process;

end;

contNb_ctl_tb.vcd
$date
  Tue Apr 20 17:00:28 2021
$end
$version
  GHDL v0
$end
$timescale
  1 fs
$end
$scope module standard $end
$upscope $end
$scope module std_logic_1164 $end
$upscope $end
$scope module numeric_std $end
$upscope $end
$scope module contnb_ctl_tb $end
$var reg 1 ! ena $end
$var reg 1 " clock $end
$var reg 4 # cont_out[3:0] $end
$var reg 1 $ data_rdy $end
$var reg 8 % data[7:0] $end
$scope module dut $end
$var reg 1 & clk_i $end
$var reg 1 ' ena_i $end
$var reg 8 ( rx_data[7:0] $end
$var reg 1 ) rx_data_rdy $end
$var reg 4 * count_o[3:0] $end
$var reg 1 + old_rx_data_rdy $end
$var reg 1 , rst $end
$var reg 1 - asc $end
$var reg 1 . ena $end
$var reg 1 / aux $end
$scope module contnb_i0 $end
$var reg 1 0 clk_i $end
$var reg 1 1 rst_i $end
$var reg 1 2 ena_i $end
$var reg 1 3 asc_i $end
$var reg 4 4 q[3:0] $end
$var reg 4 5 aux[3:0] $end
$upscope $end
$upscope $end
$upscope $end
$enddefinitions $end
#0
1!
0"
bUUUU #
0$
bUUUUUUUU %
0&
1'
bUUUUUUUU (
0)
bUUUU *
U+
U,
U-
0.
0/
00
U1
02
U3
bUUUU 4
bUUUU 5
#1000
1"
1&
0+
10
#2000
0"
0&
00
#3000
1"
1&
10
#4000
0"
0&
00
#5000
1"
1&
10
#6000
0"
0&
00
#7000
1"
1&
10
#8000
0"
0&
00
#9000
1"
1&
10
#10000
0"
b00000001 %
0&
b00000001 (
00
#11000
1"
1&
10
#12000
0"
0&
00
#13000
1"
1&
10
#14000
0"
1$
0&
1)
00
#15000
1"
1&
1+
1,
0-
10
11
03
#16000
0"
0$
0&
0)
00
#17000
1"
1&
0+
0,
10
01
b0000 5
#18000
0"
b0000 #
0&
b0000 *
00
b0000 4
#19000
1"
1&
10
#20000
0"
0&
00
#21000
1"
1&
10
#22000
0"
0&
00
#23000
1"
1&
10
#24000
0"
0&
00
#25000
1"
1&
10
#26000
0"
0&
00
#27000
1"
1&
10
#28000
0"
0&
00
#29000
1"
1&
10
#30000
0"
0&
00
#31000
1"
1&
10
#32000
0"
0&
00
#33000
1"
1&
10
#34000
0"
0&
00
#35000
1"
1&
10
#36000
0"
b00000010 %
0&
b00000010 (
00
#37000
1"
1&
10
#38000
0"
0&
00
#39000
1"
1&
10
#40000
0"
1$
0&
1)
00
#41000
1"
1&
1+
1.
1/
10
12
#42000
0"
0$
0&
0)
00
#43000
1"
1&
0+
10
b1111 5
#44000
0"
b1111 #
0&
b1111 *
00
b1111 4
#45000
1"
1&
10
b1110 5
#46000
0"
b1110 #
0&
b1110 *
00
b1110 4
#47000
1"
1&
10
b1101 5
#48000
0"
b1101 #
0&
b1101 *
00
b1101 4
#49000
1"
1&
10
b1100 5
#50000
0"
b1100 #
0&
b1100 *
00
b1100 4
#51000
1"
1&
10
b1011 5
#52000
0"
b1011 #
0&
b1011 *
00
b1011 4
#53000
1"
1&
10
b1010 5
#54000
0"
b1010 #
0&
b1010 *
00
b1010 4
#55000
1"
1&
10
b1001 5
#56000
0"
b1001 #
0&
b1001 *
00
b1001 4
#57000
1"
1&
10
b1000 5
#58000
0"
b1000 #
0&
b1000 *
00
b1000 4
#59000
1"
1&
10
b0111 5
#60000
0"
b0111 #
0&
b0111 *
00
b0111 4
#61000
1"
1&
10
b0110 5
#62000
0"
b0110 #
0&
b0110 *
00
b0110 4
#63000
1"
1&
10
b0101 5
#64000
0"
b0101 #
0&
b0101 *
00
b0101 4
#65000
1"
1&
10
b0100 5
#66000
0"
b0100 #
0&
b0100 *
00
b0100 4
#67000
1"
1&
10
b0011 5
#68000
0"
b0011 #
0&
b0011 *
00
b0011 4
#69000
1"
1&
10
b0010 5
#70000
0"
b0010 #
0&
b0010 *
00
b0010 4
#71000
1"
1&
10
b0001 5
#72000
0"
b0001 #
0&
b0001 *
00
b0001 4
#73000
1"
1&
10
b0000 5
#74000
0"
b0000 #
0&
b0000 *
00
b0000 4
#75000
1"
1&
10
b1111 5
#76000
0"
b1111 #
0&
b1111 *
00
b1111 4
#77000
1"
1&
10
b1110 5
#78000
0"
b1110 #
0&
b1110 *
00
b1110 4
#79000
1"
1&
10
b1101 5
#80000
0"
b1101 #
0&
b1101 *
00
b1101 4
#81000
1"
1&
10
b1100 5
#82000
0"
b1100 #
0&
b1100 *
00
b1100 4
#83000
1"
1&
10
b1011 5
#84000
0"
b1011 #
0&
b1011 *
00
b1011 4
#85000
1"
1&
10
b1010 5
#86000
0"
b1010 #
0&
b1010 *
00
b1010 4
#87000
1"
1&
10
b1001 5
#88000
0"
b1001 #
0&
b1001 *
00
b1001 4
#89000
1"
1&
10
b1000 5
#90000
0"
b1000 #
0&
b1000 *
00
b1000 4
#91000
1"
1&
10
b0111 5
#92000
0"
b0111 #
0&
b0111 *
00
b0111 4
#93000
1"
1&
10
b0110 5
#94000
0"
b0110 #
0&
b0110 *
00
b0110 4
#95000
1"
1&
10
b0101 5
#96000
0"
b0101 #
0&
b0101 *
00
b0101 4
#97000
1"
1&
10
b0100 5
#98000
0"
b0100 #
0&
b0100 *
00
b0100 4
#99000
1"
1&
10
b0011 5
#100000
0"
b0011 #
0&
b0011 *
00
b0011 4
#101000
1"
1&
10
b0010 5
#102000
0"
b0010 #
0&
b0010 *
00
b0010 4
#103000
1"
1&
10
b0001 5
#104000
0"
b0001 #
0&
b0001 *
00
b0001 4
#105000
1"
1&
10
b0000 5
#106000
0"
b0000 #
0&
b0000 *
00
b0000 4
#107000
1"
1&
10
b1111 5
#108000
0"
b1111 #
0&
b1111 *
00
b1111 4
#109000
1"
1&
10
b1110 5
#110000
0"
b1110 #
0&
b1110 *
00
b1110 4
#111000
1"
1&
10
b1101 5
#112000
0"
b1101 #
0&
b1101 *
00
b1101 4
#113000
1"
1&
10
b1100 5
#114000
0"
b1100 #
0&
b1100 *
00
b1100 4
#115000
1"
1&
10
b1011 5
#116000
0"
b1011 #
0&
b1011 *
00
b1011 4
#117000
1"
1&
10
b1010 5
#118000
0"
b1010 #
0&
b1010 *
00
b1010 4
#119000
1"
1&
10
b1001 5
#120000
0"
b1001 #
0&
b1001 *
00
b1001 4
#121000
1"
1&
10
b1000 5
#122000
0"
b1000 #
b00000011 %
0&
b00000011 (
b1000 *
00
b1000 4
#123000
1"
1&
10
b0111 5
#124000
0"
b0111 #
0&
b0111 *
00
b0111 4
#125000
1"
1&
10
b0110 5
#126000
0"
b0110 #
1$
0&
1)
b0110 *
00
b0110 4
#127000
1"
1&
1+
1,
10
11
b0101 5
#128000
0"
b0101 #
0$
0&
0)
b0101 *
00
b0101 4
#129000
1"
1&
0+
0,
10
01
b0000 5
#130000
0"
b0000 #
0&
b0000 *
00
b0000 4
#131000
1"
1&
10
b1111 5
#132000
0"
b1111 #
0&
b1111 *
00
b1111 4
#133000
1"
1&
10
b1110 5
#134000
0"
b1110 #
0&
b1110 *
00
b1110 4
#135000
1"
1&
10
b1101 5
#136000
0"
b1101 #
0&
b1101 *
00
b1101 4
#137000
1"
1&
10
b1100 5
#138000
0"
b1100 #
0&
b1100 *
00
b1100 4
#139000
1"
1&
10
b1011 5
#140000
0"
b1011 #
0&
b1011 *
00
b1011 4
#141000
1"
1&
10
b1010 5
#142000
0"
b1010 #
0&
b1010 *
00
b1010 4
#143000
1"
1&
10
b1001 5
#144000
0"
b1001 #
0&
b1001 *
00
b1001 4
#145000
1"
1&
10
b1000 5
#146000
0"
b1000 #
0&
b1000 *
00
b1000 4
#147000
1"
1&
10
b0111 5
#148000
0"
b0111 #
0&
b0111 *
00
b0111 4
#149000
1"
1&
10
b0110 5
#150000
0"
b0110 #
0&
b0110 *
00
b0110 4
#151000
1"
1&
10
b0101 5
#152000
0"
b0101 #
0&
b0101 *
00
b0101 4
#153000
1"
1&
10
b0100 5
#154000
0"
b0100 #
0&
b0100 *
00
b0100 4
#155000
1"
1&
10
b0011 5
#156000
0"
b0011 #
0&
b0011 *
00
b0011 4
#157000
1"
1&
10
b0010 5
#158000
0"
b0010 #
0&
b0010 *
00
b0010 4
#159000
1"
1&
10
b0001 5
#160000
0"
b0001 #
0&
b0001 *
00
b0001 4
#161000
1"
1&
10
b0000 5
#162000
0"
b0000 #
0&
b0000 *
00
b0000 4
#163000
1"
1&
10
b1111 5
#164000
0"
b1111 #
0&
b1111 *
00
b1111 4
#165000
1"
1&
10
b1110 5
#166000
0"
b1110 #
0&
b1110 *
00
b1110 4
#167000
1"
1&
10
b1101 5
#168000
0"
b1101 #
0&
b1101 *
00
b1101 4
#169000
1"
1&
10
b1100 5
#170000
0"
b1100 #
0&
b1100 *
00
b1100 4
#171000
1"
1&
10
b1011 5
#172000
0"
b1011 #
0&
b1011 *
00
b1011 4
#173000
1"
1&
10
b1010 5
#174000
0"
b1010 #
0&
b1010 *
00
b1010 4
#175000
1"
1&
10
b1001 5
#176000
0"
b1001 #
0&
b1001 *
00
b1001 4
#177000
1"
1&
10
b1000 5
#178000
0"
b1000 #
0&
b1000 *
00
b1000 4
#179000
1"
1&
10
b0111 5
#180000
0"
b0111 #
0&
b0111 *
00
b0111 4
#181000
1"
1&
10
b0110 5
#182000
0"
b0110 #
0&
b0110 *
00
b0110 4
#183000
1"
1&
10
b0101 5
#184000
0"
b0101 #
0&
b0101 *
00
b0101 4
#185000
1"
1&
10
b0100 5
#186000
0"
b0100 #
0&
b0100 *
00
b0100 4
#187000
1"
1&
10
b0011 5
#188000
0"
b0011 #
0&
b0011 *
00
b0011 4
#189000
1"
1&
10
b0010 5
#190000
0"
b0010 #
0&
b0010 *
00
b0010 4
#191000
1"
1&
10
b0001 5
#192000
0"
b0001 #
0&
b0001 *
00
b0001 4
#193000
1"
1&
10
b0000 5
#194000
0"
b0000 #
0&
b0000 *
00
b0000 4
#195000
1"
1&
10
b1111 5
#196000
0"
b1111 #
0&
b1111 *
00
b1111 4
#197000
1"
1&
10
b1110 5
#198000
0"
b1110 #
0&
b1110 *
00
b1110 4
#199000
1"
1&
10
b1101 5
#200000
0"
b1101 #
0&
b1101 *
00
b1101 4
#201000
1"
1&
10
b1100 5
#202000
0"
b1100 #
0&
b1100 *
00
b1100 4
#203000
1"
1&
10
b1011 5
#204000
0"
b1011 #
0&
b1011 *
00
b1011 4
#205000
1"
1&
10
b1010 5
#206000
0"
b1010 #
0&
b1010 *
00
b1010 4
#207000
1"
1&
10
b1001 5
#208000
0"
b1001 #
0&
b1001 *
00
b1001 4
#209000
1"
1&
10
b1000 5
#210000
0"
b1000 #
0&
b1000 *
00
b1000 4
#211000
1"
1&
10
b0111 5
#212000
0"
b0111 #
0&
b0111 *
00
b0111 4
#213000
1"
1&
10
b0110 5
#214000
0"
b0110 #
0&
b0110 *
00
b0110 4
#215000
1"
1&
10
b0101 5
#216000
0"
b0101 #
0&
b0101 *
00
b0101 4
#217000
1"
1&
10
b0100 5
#218000
0"
b0100 #
0&
b0100 *
00
b0100 4
#219000
1"
1&
10
b0011 5
#220000
0"
b0011 #
0&
b0011 *
00
b0011 4
#221000
1"
1&
10
b0010 5
#222000
0"
b0010 #
0&
b0010 *
00
b0010 4
#223000
1"
1&
10
b0001 5
#224000
0"
b0001 #
0&
b0001 *
00
b0001 4
#225000
1"
1&
10
b0000 5
#226000
0"
b0000 #
0&
b0000 *
00
b0000 4
#227000
1"
1&
10
b1111 5
#228000
0"
b1111 #
0&
b1111 *
00
b1111 4
#229000
1"
1&
10
b1110 5
#230000
0"
b1110 #
0&
b1110 *
00
b1110 4
#231000
1"
1&
10
b1101 5
#232000
0"
b1101 #
0&
b1101 *
00
b1101 4
#233000
1"
1&
10
b1100 5
#234000
0"
b1100 #
0&
b1100 *
00
b1100 4
#235000
1"
1&
10
b1011 5
#236000
0"
b1011 #
0&
b1011 *
00
b1011 4
#237000
1"
1&
10
b1010 5
#238000
0"
b1010 #
0&
b1010 *
00
b1010 4
#239000
1"
1&
10
b1001 5
#240000
0"
b1001 #
0&
b1001 *
00
b1001 4
#241000
1"
1&
10
b1000 5
#242000
0"
b1000 #
0&
b1000 *
00
b1000 4
#243000
1"
1&
10
b0111 5
#244000
0"
b0111 #
0&
b0111 *
00
b0111 4
#245000
1"
1&
10
b0110 5
#246000
0"
b0110 #
0&
b0110 *
00
b0110 4
#247000
1"
1&
10
b0101 5
#248000
0"
b0101 #
0&
b0101 *
00
b0101 4
#249000
1"
1&
10
b0100 5
#250000
0"
b0100 #
0&
b0100 *
00
b0100 4
#251000
1"
1&
10
b0011 5
#252000
0"
b0011 #
0&
b0011 *
00
b0011 4
#253000
1"
1&
10
b0010 5
#254000
0"
b0010 #
0&
b0010 *
00
b0010 4
#255000
1"
1&
10
b0001 5
#256000
0"
b0001 #
0&
b0001 *
00
b0001 4
#257000
1"
1&
10
b0000 5
#258000
0"
b0000 #
0&
b0000 *
00
b0000 4
#259000
1"
1&
10
b1111 5
#260000
0"
b1111 #
0&
b1111 *
00
b1111 4
#261000
1"
1&
10
b1110 5
#262000
0"
b1110 #
0&
b1110 *
00
b1110 4
#263000
1"
1&
10
b1101 5
#264000
0"
b1101 #
0&
b1101 *
00
b1101 4
#265000
1"
1&
10
b1100 5
#266000
0"
b1100 #
0&
b1100 *
00
b1100 4
#267000
1"
1&
10
b1011 5
#268000
0"
b1011 #
0&
b1011 *
00
b1011 4
#269000
1"
1&
10
b1010 5
#270000
0"
b1010 #
0&
b1010 *
00
b1010 4
#271000
1"
1&
10
b1001 5
#272000
0"
b1001 #
0&
b1001 *
00
b1001 4
#273000
1"
1&
10
b1000 5
#274000
0"
b1000 #
0&
b1000 *
00
b1000 4
#275000
1"
1&
10
b0111 5
#276000
0"
b0111 #
0&
b0111 *
00
b0111 4
#277000
1"
1&
10
b0110 5
#278000
0"
b0110 #
0&
b0110 *
00
b0110 4
#279000
1"
1&
10
b0101 5
#280000
0"
b0101 #
0&
b0101 *
00
b0101 4
#281000
1"
1&
10
b0100 5
#282000
0"
b0100 #
0&
b0100 *
00
b0100 4
#283000
1"
1&
10
b0011 5
#284000
0"
b0011 #
0&
b0011 *
00
b0011 4
#285000
1"
1&
10
b0010 5
#286000
0"
b0010 #
0&
b0010 *
00
b0010 4
#287000
1"
1&
10
b0001 5
#288000
0"
b0001 #
b00000100 %
0&
b00000100 (
b0001 *
00
b0001 4
#289000
1"
1&
10
b0000 5
#290000
0"
b0000 #
0&
b0000 *
00
b0000 4
#291000
1"
1&
10
b1111 5
#292000
0"
b1111 #
1$
0&
1)
b1111 *
00
b1111 4
#293000
1"
1&
1+
1-
0.
0/
10
02
13
b1110 5
#294000
0"
b1110 #
0$
0&
0)
b1110 *
00
b1110 4
#295000
1"
1&
0+
10
