contNb.vhd
library IEEE;
use IEEE.std_logic_1164.all;
use IEEE.numeric_std.all;

entity contNb is
    generic(N:natural :=4);
	port(
		clk_i: in std_logic;
		rst_i: in std_logic;
		ena_i: in std_logic;
        asc_i: in std_logic;
		q: out std_logic_vector(N-1 downto 0)
	);
end;

architecture contNb_arq of contNb is
    signal aux: unsigned(N-1 downto 0);
begin

    process(clk_i)
    
    begin
        if rising_edge(clk_i) then
            if rst_i = '1' then
                aux <= (others => '0');
                --count <= (others => '0');
            elsif ena_i = '1' then
                if asc_i = '1' then
                    aux <= aux + 1;
                    --count <= count + '1';
                else
                    aux <= aux - 1;
                    --count <= count - '1';
                end if;
            end if;
        end if;
        --q <= count;
        q <= std_logic_vector(aux);
    end process;

    
            
end;

contNb_tb.vhd
library IEEE;
use IEEE.std_logic_1164.all;
use IEEE.numeric_std.all;

entity contNb_tb is
end;

architecture contNb_tb_arq of contNb_tb is

	component contNb is
		generic(N:natural :=4);
		port(
			clk_i: in std_logic;
			rst_i: in std_logic;
			ena_i: in std_logic;
			asc_i: in std_logic;
			q: out std_logic_vector(N-1 downto 0)
		);
	end component;

	constant N_used: integer :=4;
	constant half_period: time := 10 ns;

	signal clock : std_logic := '1';
	signal reset: std_logic := '0';
	signal enable: std_logic := '1';
	signal asc: std_logic := '1';
	signal cont_out: std_logic_vector(N_used-1 downto 0);
	
begin

	DUT: contNb
		generic map(N => N_used)
		port map(
			clk_i => clock,
			rst_i => reset,
			ena_i => enable,
			asc_i => asc,
			q 	  => cont_out
		);


	clk_process :process
	begin
		clock <= '0';
		wait for half_period;  --for half of clock period clk stays at '0'.
		clock <= '1';
		wait for half_period;  --for next half of clock period clk stays at '1'.
	end process;
	
	stim_proc: process
	begin        
		 wait for half_period*2*5; --wait for 5 clock cycles.
		 reset <= '1';
		 wait for half_period*2*5; --wait for 5 clock cycles.
		 reset <= '0';
		 wait for half_period*2*40; --wait for 40 clock cycles.
		 asc <= '0';
		 wait for half_period*2*40; --wait for 40 clock cycles.
		 assert false report "Test: OK" severity failure;
   end process;

end;

contNb_tb.vcd
$date
  Tue Apr 20 10:35:57 2021
$end
$version
  GHDL v0
$end
$timescale
  1 fs
$end
$scope module standard $end
$upscope $end
$scope module std_logic_1164 $end
$upscope $end
$scope module numeric_std $end
$upscope $end
$scope module contnb_tb $end
$var reg 1 ! clock $end
$var reg 1 " reset $end
$var reg 1 # enable $end
$var reg 1 $ asc $end
$var reg 4 % cont_out[3:0] $end
$scope module dut $end
$var reg 1 & clk_i $end
$var reg 1 ' rst_i $end
$var reg 1 ( ena_i $end
$var reg 1 ) asc_i $end
$var reg 4 * q[3:0] $end
$var reg 4 + aux[3:0] $end
$upscope $end
$upscope $end
$enddefinitions $end
#0
0!
0"
1#
1$
bUUUU %
0&
0'
1(
1)
bUUUU *
bUUUU +
#10000000
1!
1&
bXXXX +
#20000000
0!
bXXXX %
0&
bXXXX *
#30000000
1!
1&
#40000000
0!
0&
#50000000
1!
1&
#60000000
0!
0&
#70000000
1!
1&
#80000000
0!
0&
#90000000
1!
1&
#100000000
0!
1"
0&
1'
#110000000
1!
1&
b0000 +
#120000000
0!
b0000 %
0&
b0000 *
#130000000
1!
1&
#140000000
0!
0&
#150000000
1!
1&
#160000000
0!
0&
#170000000
1!
1&
#180000000
0!
0&
#190000000
1!
1&
#200000000
0!
0"
0&
0'
#210000000
1!
1&
b0001 +
#220000000
0!
b0001 %
0&
b0001 *
#230000000
1!
1&
b0010 +
#240000000
0!
b0010 %
0&
b0010 *
#250000000
1!
1&
b0011 +
#260000000
0!
b0011 %
0&
b0011 *
#270000000
1!
1&
b0100 +
#280000000
0!
b0100 %
0&
b0100 *
#290000000
1!
1&
b0101 +
#300000000
0!
b0101 %
0&
b0101 *
#310000000
1!
1&
b0110 +
#320000000
0!
b0110 %
0&
b0110 *
#330000000
1!
1&
b0111 +
#340000000
0!
b0111 %
0&
b0111 *
#350000000
1!
1&
b1000 +
#360000000
0!
b1000 %
0&
b1000 *
#370000000
1!
1&
b1001 +
#380000000
0!
b1001 %
0&
b1001 *
#390000000
1!
1&
b1010 +
#400000000
0!
b1010 %
0&
b1010 *
#410000000
1!
1&
b1011 +
#420000000
0!
b1011 %
0&
b1011 *
#430000000
1!
1&
b1100 +
#440000000
0!
b1100 %
0&
b1100 *
#450000000
1!
1&
b1101 +
#460000000
0!
b1101 %
0&
b1101 *
#470000000
1!
1&
b1110 +
#480000000
0!
b1110 %
0&
b1110 *
#490000000
1!
1&
b1111 +
#500000000
0!
b1111 %
0&
b1111 *
#510000000
1!
1&
b0000 +
#520000000
0!
b0000 %
0&
b0000 *
#530000000
1!
1&
b0001 +
#540000000
0!
b0001 %
0&
b0001 *
#550000000
1!
1&
b0010 +
#560000000
0!
b0010 %
0&
b0010 *
#570000000
1!
1&
b0011 +
#580000000
0!
b0011 %
0&
b0011 *
#590000000
1!
1&
b0100 +
#600000000
0!
b0100 %
0&
b0100 *
#610000000
1!
1&
b0101 +
#620000000
0!
b0101 %
0&
b0101 *
#630000000
1!
1&
b0110 +
#640000000
0!
b0110 %
0&
b0110 *
#650000000
1!
1&
b0111 +
#660000000
0!
b0111 %
0&
b0111 *
#670000000
1!
1&
b1000 +
#680000000
0!
b1000 %
0&
b1000 *
#690000000
1!
1&
b1001 +
#700000000
0!
b1001 %
0&
b1001 *
#710000000
1!
1&
b1010 +
#720000000
0!
b1010 %
0&
b1010 *
#730000000
1!
1&
b1011 +
#740000000
0!
b1011 %
0&
b1011 *
#750000000
1!
1&
b1100 +
#760000000
0!
b1100 %
0&
b1100 *
#770000000
1!
1&
b1101 +
#780000000
0!
b1101 %
0&
b1101 *
#790000000
1!
1&
b1110 +
#800000000
0!
b1110 %
0&
b1110 *
#810000000
1!
1&
b1111 +
#820000000
0!
b1111 %
0&
b1111 *
#830000000
1!
1&
b0000 +
#840000000
0!
b0000 %
0&
b0000 *
#850000000
1!
1&
b0001 +
#860000000
0!
b0001 %
0&
b0001 *
#870000000
1!
1&
b0010 +
#880000000
0!
b0010 %
0&
b0010 *
#890000000
1!
1&
b0011 +
#900000000
0!
b0011 %
0&
b0011 *
#910000000
1!
1&
b0100 +
#920000000
0!
b0100 %
0&
b0100 *
#930000000
1!
1&
b0101 +
#940000000
0!
b0101 %
0&
b0101 *
#950000000
1!
1&
b0110 +
#960000000
0!
b0110 %
0&
b0110 *
#970000000
1!
1&
b0111 +
#980000000
0!
b0111 %
0&
b0111 *
#990000000
1!
1&
b1000 +
#1000000000
0!
0$
b1000 %
0&
0)
b1000 *
#1010000000
1!
1&
b0111 +
#1020000000
0!
b0111 %
0&
b0111 *
#1030000000
1!
1&
b0110 +
#1040000000
0!
b0110 %
0&
b0110 *
#1050000000
1!
1&
b0101 +
#1060000000
0!
b0101 %
0&
b0101 *
#1070000000
1!
1&
b0100 +
#1080000000
0!
b0100 %
0&
b0100 *
#1090000000
1!
1&
b0011 +
#1100000000
0!
b0011 %
0&
b0011 *
#1110000000
1!
1&
b0010 +
#1120000000
0!
b0010 %
0&
b0010 *
#1130000000
1!
1&
b0001 +
#1140000000
0!
b0001 %
0&
b0001 *
#1150000000
1!
1&
b0000 +
#1160000000
0!
b0000 %
0&
b0000 *
#1170000000
1!
1&
b1111 +
#1180000000
0!
b1111 %
0&
b1111 *
#1190000000
1!
1&
b1110 +
#1200000000
0!
b1110 %
0&
b1110 *
#1210000000
1!
1&
b1101 +
#1220000000
0!
b1101 %
0&
b1101 *
#1230000000
1!
1&
b1100 +
#1240000000
0!
b1100 %
0&
b1100 *
#1250000000
1!
1&
b1011 +
#1260000000
0!
b1011 %
0&
b1011 *
#1270000000
1!
1&
b1010 +
#1280000000
0!
b1010 %
0&
b1010 *
#1290000000
1!
1&
b1001 +
#1300000000
0!
b1001 %
0&
b1001 *
#1310000000
1!
1&
b1000 +
#1320000000
0!
b1000 %
0&
b1000 *
#1330000000
1!
1&
b0111 +
#1340000000
0!
b0111 %
0&
b0111 *
#1350000000
1!
1&
b0110 +
#1360000000
0!
b0110 %
0&
b0110 *
#1370000000
1!
1&
b0101 +
#1380000000
0!
b0101 %
0&
b0101 *
#1390000000
1!
1&
b0100 +
#1400000000
0!
b0100 %
0&
b0100 *
#1410000000
1!
1&
b0011 +
#1420000000
0!
b0011 %
0&
b0011 *
#1430000000
1!
1&
b0010 +
#1440000000
0!
b0010 %
0&
b0010 *
#1450000000
1!
1&
b0001 +
#1460000000
0!
b0001 %
0&
b0001 *
#1470000000
1!
1&
b0000 +
#1480000000
0!
b0000 %
0&
b0000 *
#1490000000
1!
1&
b1111 +
#1500000000
0!
b1111 %
0&
b1111 *
#1510000000
1!
1&
b1110 +
#1520000000
0!
b1110 %
0&
b1110 *
#1530000000
1!
1&
b1101 +
#1540000000
0!
b1101 %
0&
b1101 *
#1550000000
1!
1&
b1100 +
#1560000000
0!
b1100 %
0&
b1100 *
#1570000000
1!
1&
b1011 +
#1580000000
0!
b1011 %
0&
b1011 *
#1590000000
1!
1&
b1010 +
#1600000000
0!
b1010 %
0&
b1010 *
#1610000000
1!
1&
b1001 +
#1620000000
0!
b1001 %
0&
b1001 *
#1630000000
1!
1&
b1000 +
#1640000000
0!
b1000 %
0&
b1000 *
#1650000000
1!
1&
b0111 +
#1660000000
0!
b0111 %
0&
b0111 *
#1670000000
1!
1&
b0110 +
#1680000000
0!
b0110 %
0&
b0110 *
#1690000000
1!
1&
b0101 +
#1700000000
0!
b0101 %
0&
b0101 *
#1710000000
1!
1&
b0100 +
#1720000000
0!
b0100 %
0&
b0100 *
#1730000000
1!
1&
b0011 +
#1740000000
0!
b0011 %
0&
b0011 *
#1750000000
1!
1&
b0010 +
#1760000000
0!
b0010 %
0&
b0010 *
#1770000000
1!
1&
b0001 +
#1780000000
0!
b0001 %
0&
b0001 *
#1790000000
1!
1&
b0000 +
