contNb.vhd
library IEEE;
use IEEE.std_logic_1164.all;
use IEEE.numeric_std.all;

entity contNb is
    generic(N:natural :=4);
	port(
		clk_i: in std_logic;
		rst_i: in std_logic;
		ena_i: in std_logic;
        asc_i: in std_logic;
		q: out std_logic_vector(N-1 downto 0)
	);
end;

architecture contNb_arq of contNb is
    signal aux: unsigned(N-1 downto 0);
begin

    process(clk_i)
    
    begin
        if rising_edge(clk_i) then
            if rst_i = '1' then
                aux <= (others => '0');
                --count <= (others => '0');
            elsif ena_i = '1' then
                if asc_i = '1' then
                    aux <= aux + 1;
                    --count <= count + '1';
                else
                    aux <= aux - 1;
                    --count <= count - '1';
                end if;
            end if;
        end if;
        --q <= count;
        q <= std_logic_vector(aux);
    end process;

    
            
end;

contNb_ctl.vhd
-----------------------------------------------------------------------------
--  
--  
--
--  Project  : UART controlled counter
--  Module   : contNb_ctl.v
--  Parent   : uart_cont.v
--  Children : None
--
--  Description: 
--     LED output generator
--
--  Parameters:
--     None
--
--  Local Parameters:
--
--  Notes       : 
--
--  Multicycle and False Paths
--    None
--

library IEEE;
use IEEE.std_logic_1164.all;

entity contNb_ctl is
	generic(N:natural :=4);
	port(
		clk_i:			in std_logic;						-- Clock input
		rx_data:		in std_logic_vector(7 downto 0);	-- 8 bit data input
		rx_data_rdy:	in std_logic;						-- valid when rx_data_rdy is asserted
		count_o:		out std_logic_vector(N-1 downto 0)	-- The counter outputs
	);
end;


architecture contNb_ctl_arq of contNb_ctl is

	component contNb is
		generic(N:natural :=4);
		port(
			clk_i: in std_logic;
			rst_i: in std_logic;
			ena_i: in std_logic;
			asc_i: in std_logic;
			q: out std_logic_vector(N-1 downto 0)
		);
	end component;

	signal old_rx_data_rdy: std_logic;
	signal char_data: std_logic_vector(7 downto 0);
	signal rst,asc,ena: std_logic;

begin

	inst_contNb: contNb
		generic map(N => N)
		port map(
			clk_i => clk_i,
			rst_i => rst,
			ena_i => ena,
			asc_i => asc,
			q 	  => count_o
		);

	process(clk_i)
	begin
		if rising_edge(clk_i) then
			if rst = '1' then
				old_rx_data_rdy <= '0';
				char_data       <= "00000000";
				rst <= '0';
			else
				-- Capture the value of rx_data_rdy for edge detection
				old_rx_data_rdy <= rx_data_rdy;
				-- If rising edge of rx_data_rdy, capture rx_data
				if (rx_data_rdy = '1' and old_rx_data_rdy = '0') then
					char_data <= rx_data;
					rst <= rx_data(0);
					ena <= rx_data(1);
					asc <= rx_data(2);
				end if;
			end if;	-- if !rst
		end if;
	end process;
end;

contNb_ctl_tb.vhd
library IEEE;
use IEEE.std_logic_1164.all;
use IEEE.numeric_std.all;

entity contNb_ctl_tb is
end;

architecture contNb_ctl_tb_arq of contNb_ctl_tb is

    component contNb_ctl is
        generic(N:natural :=4);
        port(
            clk_i:			in std_logic;						-- Clock input
            rx_data:		in std_logic_vector(7 downto 0);	-- 8 bit data input
            rx_data_rdy:	in std_logic;						-- valid when rx_data_rdy is asserted
            count_o:		out std_logic_vector(N-1 downto 0)	-- The counter outputs
        );
    end component;

	constant N_used: integer :=4;
	constant half_period: time := 1 ps;--10 ns;

	signal clock : std_logic := '1';
	signal cont_out: std_logic_vector(N_used-1 downto 0);
    signal data_rdy: std_logic := '0';
    signal data: std_logic_vector(7 downto 0);
	
begin

	DUT: contNb_ctl
		generic map(N => N_used)
		port map(
			clk_i => clock,
			rx_data => data,
			rx_data_rdy => data_rdy,
			count_o  => cont_out
		);


	clk_process :process
	begin
		clock <= '0';
		wait for half_period;  --for half of clock period clk stays at '0'.
		clock <= '1';
		wait for half_period;  --for next half of clock period clk stays at '1'.
	end process;
	
	stim_proc: process
	begin        
		wait for half_period*2*5; --wait for 5 clock cycles.
       	data <= "00000001"; -- asc=0 ena=0 rst=1
        wait for half_period*2*2; --wait for 2 clock cycles.
      	data_rdy <= '1';
        wait for half_period*2*1; --wait for 1 clock cycles.
        data_rdy <= '0';

		wait for half_period*2*10; --wait for 10 clock cycles.
		data <= "00000010"; -- asc=0 ena=1 rst=0
        wait for half_period*2*2; --wait for 2 clock cycles.
        data_rdy <= '1';
        wait for half_period*2*1; --wait for 1 clock cycles.
        data_rdy <= '0';

		wait for half_period*2*40; --wait for 40 clock cycles.
		data <= "00000011"; -- asc=0 ena=1 rst=1
        wait for half_period*2*2; --wait for 2 clock cycles.
        data_rdy <= '1';
        wait for half_period*2*1; --wait for 1 clock cycles.
        data_rdy <= '0';
		wait for half_period*2*40; --wait for 40 clock cycles.

		wait for half_period*2*40; --wait for 40 clock cycles.
		data <= "00000100"; -- asc=1 ena=0 rst=0
        wait for half_period*2*2; --wait for 2 clock cycles.
        data_rdy <= '1';
        wait for half_period*2*1; --wait for 1 clock cycles.
        data_rdy <= '0';
		wait for half_period*2*40; --wait for 40 clock cycles.

		wait for half_period*2*40; --wait for 40 clock cycles.
		data <= "00000101"; -- asc=1 ena=0 rst=1
        wait for half_period*2*2; --wait for 2 clock cycles.
        data_rdy <= '1';
        wait for half_period*2*1; --wait for 1 clock cycles.
        data_rdy <= '0';
		wait for half_period*2*40; --wait for 40 clock cycles.

		wait for half_period*2*40; --wait for 40 clock cycles.
		data <= "00000110"; -- asc=1 ena=1 rst=0
        wait for half_period*2*2; --wait for 2 clock cycles.
        data_rdy <= '1';
        wait for half_period*2*1; --wait for 1 clock cycles.
        data_rdy <= '0';
		wait for half_period*2*40; --wait for 40 clock cycles.

		wait for half_period*2*40; --wait for 40 clock cycles.
		data <= "00000111"; -- asc=1 ena=1 rst=1
        wait for half_period*2*2; --wait for 2 clock cycles.
        data_rdy <= '1';
        wait for half_period*2*1; --wait for 1 clock cycles.
        data_rdy <= '0';
		wait for half_period*2*40; --wait for 40 clock cycles.
		assert false report "Test: OK" severity failure;
   end process;

end;

contNb_ctl_tb.vcd
$date
  Tue Apr 20 10:43:57 2021
$end
$version
  GHDL v0
$end
$timescale
  1 fs
$end
$scope module standard $end
$upscope $end
$scope module std_logic_1164 $end
$upscope $end
$scope module numeric_std $end
$upscope $end
$scope module contnb_ctl_tb $end
$var reg 1 ! clock $end
$var reg 4 " cont_out[3:0] $end
$var reg 1 # data_rdy $end
$var reg 8 $ data[7:0] $end
$scope module dut $end
$var reg 1 % clk_i $end
$var reg 8 & rx_data[7:0] $end
$var reg 1 ' rx_data_rdy $end
$var reg 4 ( count_o[3:0] $end
$var reg 1 ) old_rx_data_rdy $end
$var reg 8 * char_data[7:0] $end
$var reg 1 + rst $end
$var reg 1 , asc $end
$var reg 1 - ena $end
$scope module inst_contnb $end
$var reg 1 . clk_i $end
$var reg 1 / rst_i $end
$var reg 1 0 ena_i $end
$var reg 1 1 asc_i $end
$var reg 4 2 q[3:0] $end
$var reg 4 3 aux[3:0] $end
$upscope $end
$upscope $end
$upscope $end
$enddefinitions $end
#0
0!
bUUUU "
0#
bUUUUUUUU $
0%
bUUUUUUUU &
0'
bUUUU (
U)
bUUUUUUUU *
U+
U,
U-
0.
U/
U0
U1
bUUUU 2
bUUUU 3
#1000
1!
1%
0)
1.
#2000
0!
0%
0.
#3000
1!
1%
1.
#4000
0!
0%
0.
#5000
1!
1%
1.
#6000
0!
0%
0.
#7000
1!
1%
1.
#8000
0!
0%
0.
#9000
1!
1%
1.
#10000
0!
b00000001 $
0%
b00000001 &
0.
#11000
1!
1%
1.
#12000
0!
0%
0.
#13000
1!
1%
1.
#14000
0!
1#
0%
1'
0.
#15000
1!
1%
1)
b00000001 *
1+
0,
0-
1.
1/
00
01
#16000
0!
0#
0%
0'
0.
#17000
1!
1%
0)
b00000000 *
0+
1.
0/
b0000 3
#18000
0!
b0000 "
0%
b0000 (
0.
b0000 2
#19000
1!
1%
1.
#20000
0!
0%
0.
#21000
1!
1%
1.
#22000
0!
0%
0.
#23000
1!
1%
1.
#24000
0!
0%
0.
#25000
1!
1%
1.
#26000
0!
0%
0.
#27000
1!
1%
1.
#28000
0!
0%
0.
#29000
1!
1%
1.
#30000
0!
0%
0.
#31000
1!
1%
1.
#32000
0!
0%
0.
#33000
1!
1%
1.
#34000
0!
0%
0.
#35000
1!
1%
1.
#36000
0!
b00000010 $
0%
b00000010 &
0.
#37000
1!
1%
1.
#38000
0!
0%
0.
#39000
1!
1%
1.
#40000
0!
1#
0%
1'
0.
#41000
1!
1%
1)
b00000010 *
1-
1.
10
#42000
0!
0#
0%
0'
0.
#43000
1!
1%
0)
1.
b1111 3
#44000
0!
b1111 "
0%
b1111 (
0.
b1111 2
#45000
1!
1%
1.
b1110 3
#46000
0!
b1110 "
0%
b1110 (
0.
b1110 2
#47000
1!
1%
1.
b1101 3
#48000
0!
b1101 "
0%
b1101 (
0.
b1101 2
#49000
1!
1%
1.
b1100 3
#50000
0!
b1100 "
0%
b1100 (
0.
b1100 2
#51000
1!
1%
1.
b1011 3
#52000
0!
b1011 "
0%
b1011 (
0.
b1011 2
#53000
1!
1%
1.
b1010 3
#54000
0!
b1010 "
0%
b1010 (
0.
b1010 2
#55000
1!
1%
1.
b1001 3
#56000
0!
b1001 "
0%
b1001 (
0.
b1001 2
#57000
1!
1%
1.
b1000 3
#58000
0!
b1000 "
0%
b1000 (
0.
b1000 2
#59000
1!
1%
1.
b0111 3
#60000
0!
b0111 "
0%
b0111 (
0.
b0111 2
#61000
1!
1%
1.
b0110 3
#62000
0!
b0110 "
0%
b0110 (
0.
b0110 2
#63000
1!
1%
1.
b0101 3
#64000
0!
b0101 "
0%
b0101 (
0.
b0101 2
#65000
1!
1%
1.
b0100 3
#66000
0!
b0100 "
0%
b0100 (
0.
b0100 2
#67000
1!
1%
1.
b0011 3
#68000
0!
b0011 "
0%
b0011 (
0.
b0011 2
#69000
1!
1%
1.
b0010 3
#70000
0!
b0010 "
0%
b0010 (
0.
b0010 2
#71000
1!
1%
1.
b0001 3
#72000
0!
b0001 "
0%
b0001 (
0.
b0001 2
#73000
1!
1%
1.
b0000 3
#74000
0!
b0000 "
0%
b0000 (
0.
b0000 2
#75000
1!
1%
1.
b1111 3
#76000
0!
b1111 "
0%
b1111 (
0.
b1111 2
#77000
1!
1%
1.
b1110 3
#78000
0!
b1110 "
0%
b1110 (
0.
b1110 2
#79000
1!
1%
1.
b1101 3
#80000
0!
b1101 "
0%
b1101 (
0.
b1101 2
#81000
1!
1%
1.
b1100 3
#82000
0!
b1100 "
0%
b1100 (
0.
b1100 2
#83000
1!
1%
1.
b1011 3
#84000
0!
b1011 "
0%
b1011 (
0.
b1011 2
#85000
1!
1%
1.
b1010 3
#86000
0!
b1010 "
0%
b1010 (
0.
b1010 2
#87000
1!
1%
1.
b1001 3
#88000
0!
b1001 "
0%
b1001 (
0.
b1001 2
#89000
1!
1%
1.
b1000 3
#90000
0!
b1000 "
0%
b1000 (
0.
b1000 2
#91000
1!
1%
1.
b0111 3
#92000
0!
b0111 "
0%
b0111 (
0.
b0111 2
#93000
1!
1%
1.
b0110 3
#94000
0!
b0110 "
0%
b0110 (
0.
b0110 2
#95000
1!
1%
1.
b0101 3
#96000
0!
b0101 "
0%
b0101 (
0.
b0101 2
#97000
1!
1%
1.
b0100 3
#98000
0!
b0100 "
0%
b0100 (
0.
b0100 2
#99000
1!
1%
1.
b0011 3
#100000
0!
b0011 "
0%
b0011 (
0.
b0011 2
#101000
1!
1%
1.
b0010 3
#102000
0!
b0010 "
0%
b0010 (
0.
b0010 2
#103000
1!
1%
1.
b0001 3
#104000
0!
b0001 "
0%
b0001 (
0.
b0001 2
#105000
1!
1%
1.
b0000 3
#106000
0!
b0000 "
0%
b0000 (
0.
b0000 2
#107000
1!
1%
1.
b1111 3
#108000
0!
b1111 "
0%
b1111 (
0.
b1111 2
#109000
1!
1%
1.
b1110 3
#110000
0!
b1110 "
0%
b1110 (
0.
b1110 2
#111000
1!
1%
1.
b1101 3
#112000
0!
b1101 "
0%
b1101 (
0.
b1101 2
#113000
1!
1%
1.
b1100 3
#114000
0!
b1100 "
0%
b1100 (
0.
b1100 2
#115000
1!
1%
1.
b1011 3
#116000
0!
b1011 "
0%
b1011 (
0.
b1011 2
#117000
1!
1%
1.
b1010 3
#118000
0!
b1010 "
0%
b1010 (
0.
b1010 2
#119000
1!
1%
1.
b1001 3
#120000
0!
b1001 "
0%
b1001 (
0.
b1001 2
#121000
1!
1%
1.
b1000 3
#122000
0!
b1000 "
b00000011 $
0%
b00000011 &
b1000 (
0.
b1000 2
#123000
1!
1%
1.
b0111 3
#124000
0!
b0111 "
0%
b0111 (
0.
b0111 2
#125000
1!
1%
1.
b0110 3
#126000
0!
b0110 "
1#
0%
1'
b0110 (
0.
b0110 2
#127000
1!
1%
1)
b00000011 *
1+
1.
1/
b0101 3
#128000
0!
b0101 "
0#
0%
0'
b0101 (
0.
b0101 2
#129000
1!
1%
0)
b00000000 *
0+
1.
0/
b0000 3
#130000
0!
b0000 "
0%
b0000 (
0.
b0000 2
#131000
1!
1%
1.
b1111 3
#132000
0!
b1111 "
0%
b1111 (
0.
b1111 2
#133000
1!
1%
1.
b1110 3
#134000
0!
b1110 "
0%
b1110 (
0.
b1110 2
#135000
1!
1%
1.
b1101 3
#136000
0!
b1101 "
0%
b1101 (
0.
b1101 2
#137000
1!
1%
1.
b1100 3
#138000
0!
b1100 "
0%
b1100 (
0.
b1100 2
#139000
1!
1%
1.
b1011 3
#140000
0!
b1011 "
0%
b1011 (
0.
b1011 2
#141000
1!
1%
1.
b1010 3
#142000
0!
b1010 "
0%
b1010 (
0.
b1010 2
#143000
1!
1%
1.
b1001 3
#144000
0!
b1001 "
0%
b1001 (
0.
b1001 2
#145000
1!
1%
1.
b1000 3
#146000
0!
b1000 "
0%
b1000 (
0.
b1000 2
#147000
1!
1%
1.
b0111 3
#148000
0!
b0111 "
0%
b0111 (
0.
b0111 2
#149000
1!
1%
1.
b0110 3
#150000
0!
b0110 "
0%
b0110 (
0.
b0110 2
#151000
1!
1%
1.
b0101 3
#152000
0!
b0101 "
0%
b0101 (
0.
b0101 2
#153000
1!
1%
1.
b0100 3
#154000
0!
b0100 "
0%
b0100 (
0.
b0100 2
#155000
1!
1%
1.
b0011 3
#156000
0!
b0011 "
0%
b0011 (
0.
b0011 2
#157000
1!
1%
1.
b0010 3
#158000
0!
b0010 "
0%
b0010 (
0.
b0010 2
#159000
1!
1%
1.
b0001 3
#160000
0!
b0001 "
0%
b0001 (
0.
b0001 2
#161000
1!
1%
1.
b0000 3
#162000
0!
b0000 "
0%
b0000 (
0.
b0000 2
#163000
1!
1%
1.
b1111 3
#164000
0!
b1111 "
0%
b1111 (
0.
b1111 2
#165000
1!
1%
1.
b1110 3
#166000
0!
b1110 "
0%
b1110 (
0.
b1110 2
#167000
1!
1%
1.
b1101 3
#168000
0!
b1101 "
0%
b1101 (
0.
b1101 2
#169000
1!
1%
1.
b1100 3
#170000
0!
b1100 "
0%
b1100 (
0.
b1100 2
#171000
1!
1%
1.
b1011 3
#172000
0!
b1011 "
0%
b1011 (
0.
b1011 2
#173000
1!
1%
1.
b1010 3
#174000
0!
b1010 "
0%
b1010 (
0.
b1010 2
#175000
1!
1%
1.
b1001 3
#176000
0!
b1001 "
0%
b1001 (
0.
b1001 2
#177000
1!
1%
1.
b1000 3
#178000
0!
b1000 "
0%
b1000 (
0.
b1000 2
#179000
1!
1%
1.
b0111 3
#180000
0!
b0111 "
0%
b0111 (
0.
b0111 2
#181000
1!
1%
1.
b0110 3
#182000
0!
b0110 "
0%
b0110 (
0.
b0110 2
#183000
1!
1%
1.
b0101 3
#184000
0!
b0101 "
0%
b0101 (
0.
b0101 2
#185000
1!
1%
1.
b0100 3
#186000
0!
b0100 "
0%
b0100 (
0.
b0100 2
#187000
1!
1%
1.
b0011 3
#188000
0!
b0011 "
0%
b0011 (
0.
b0011 2
#189000
1!
1%
1.
b0010 3
#190000
0!
b0010 "
0%
b0010 (
0.
b0010 2
#191000
1!
1%
1.
b0001 3
#192000
0!
b0001 "
0%
b0001 (
0.
b0001 2
#193000
1!
1%
1.
b0000 3
#194000
0!
b0000 "
0%
b0000 (
0.
b0000 2
#195000
1!
1%
1.
b1111 3
#196000
0!
b1111 "
0%
b1111 (
0.
b1111 2
#197000
1!
1%
1.
b1110 3
#198000
0!
b1110 "
0%
b1110 (
0.
b1110 2
#199000
1!
1%
1.
b1101 3
#200000
0!
b1101 "
0%
b1101 (
0.
b1101 2
#201000
1!
1%
1.
b1100 3
#202000
0!
b1100 "
0%
b1100 (
0.
b1100 2
#203000
1!
1%
1.
b1011 3
#204000
0!
b1011 "
0%
b1011 (
0.
b1011 2
#205000
1!
1%
1.
b1010 3
#206000
0!
b1010 "
0%
b1010 (
0.
b1010 2
#207000
1!
1%
1.
b1001 3
#208000
0!
b1001 "
0%
b1001 (
0.
b1001 2
#209000
1!
1%
1.
b1000 3
#210000
0!
b1000 "
0%
b1000 (
0.
b1000 2
#211000
1!
1%
1.
b0111 3
#212000
0!
b0111 "
0%
b0111 (
0.
b0111 2
#213000
1!
1%
1.
b0110 3
#214000
0!
b0110 "
0%
b0110 (
0.
b0110 2
#215000
1!
1%
1.
b0101 3
#216000
0!
b0101 "
0%
b0101 (
0.
b0101 2
#217000
1!
1%
1.
b0100 3
#218000
0!
b0100 "
0%
b0100 (
0.
b0100 2
#219000
1!
1%
1.
b0011 3
#220000
0!
b0011 "
0%
b0011 (
0.
b0011 2
#221000
1!
1%
1.
b0010 3
#222000
0!
b0010 "
0%
b0010 (
0.
b0010 2
#223000
1!
1%
1.
b0001 3
#224000
0!
b0001 "
0%
b0001 (
0.
b0001 2
#225000
1!
1%
1.
b0000 3
#226000
0!
b0000 "
0%
b0000 (
0.
b0000 2
#227000
1!
1%
1.
b1111 3
#228000
0!
b1111 "
0%
b1111 (
0.
b1111 2
#229000
1!
1%
1.
b1110 3
#230000
0!
b1110 "
0%
b1110 (
0.
b1110 2
#231000
1!
1%
1.
b1101 3
#232000
0!
b1101 "
0%
b1101 (
0.
b1101 2
#233000
1!
1%
1.
b1100 3
#234000
0!
b1100 "
0%
b1100 (
0.
b1100 2
#235000
1!
1%
1.
b1011 3
#236000
0!
b1011 "
0%
b1011 (
0.
b1011 2
#237000
1!
1%
1.
b1010 3
#238000
0!
b1010 "
0%
b1010 (
0.
b1010 2
#239000
1!
1%
1.
b1001 3
#240000
0!
b1001 "
0%
b1001 (
0.
b1001 2
#241000
1!
1%
1.
b1000 3
#242000
0!
b1000 "
0%
b1000 (
0.
b1000 2
#243000
1!
1%
1.
b0111 3
#244000
0!
b0111 "
0%
b0111 (
0.
b0111 2
#245000
1!
1%
1.
b0110 3
#246000
0!
b0110 "
0%
b0110 (
0.
b0110 2
#247000
1!
1%
1.
b0101 3
#248000
0!
b0101 "
0%
b0101 (
0.
b0101 2
#249000
1!
1%
1.
b0100 3
#250000
0!
b0100 "
0%
b0100 (
0.
b0100 2
#251000
1!
1%
1.
b0011 3
#252000
0!
b0011 "
0%
b0011 (
0.
b0011 2
#253000
1!
1%
1.
b0010 3
#254000
0!
b0010 "
0%
b0010 (
0.
b0010 2
#255000
1!
1%
1.
b0001 3
#256000
0!
b0001 "
0%
b0001 (
0.
b0001 2
#257000
1!
1%
1.
b0000 3
#258000
0!
b0000 "
0%
b0000 (
0.
b0000 2
#259000
1!
1%
1.
b1111 3
#260000
0!
b1111 "
0%
b1111 (
0.
b1111 2
#261000
1!
1%
1.
b1110 3
#262000
0!
b1110 "
0%
b1110 (
0.
b1110 2
#263000
1!
1%
1.
b1101 3
#264000
0!
b1101 "
0%
b1101 (
0.
b1101 2
#265000
1!
1%
1.
b1100 3
#266000
0!
b1100 "
0%
b1100 (
0.
b1100 2
#267000
1!
1%
1.
b1011 3
#268000
0!
b1011 "
0%
b1011 (
0.
b1011 2
#269000
1!
1%
1.
b1010 3
#270000
0!
b1010 "
0%
b1010 (
0.
b1010 2
#271000
1!
1%
1.
b1001 3
#272000
0!
b1001 "
0%
b1001 (
0.
b1001 2
#273000
1!
1%
1.
b1000 3
#274000
0!
b1000 "
0%
b1000 (
0.
b1000 2
#275000
1!
1%
1.
b0111 3
#276000
0!
b0111 "
0%
b0111 (
0.
b0111 2
#277000
1!
1%
1.
b0110 3
#278000
0!
b0110 "
0%
b0110 (
0.
b0110 2
#279000
1!
1%
1.
b0101 3
#280000
0!
b0101 "
0%
b0101 (
0.
b0101 2
#281000
1!
1%
1.
b0100 3
#282000
0!
b0100 "
0%
b0100 (
0.
b0100 2
#283000
1!
1%
1.
b0011 3
#284000
0!
b0011 "
0%
b0011 (
0.
b0011 2
#285000
1!
1%
1.
b0010 3
#286000
0!
b0010 "
0%
b0010 (
0.
b0010 2
#287000
1!
1%
1.
b0001 3
#288000
0!
b0001 "
b00000100 $
0%
b00000100 &
b0001 (
0.
b0001 2
#289000
1!
1%
1.
b0000 3
#290000
0!
b0000 "
0%
b0000 (
0.
b0000 2
#291000
1!
1%
1.
b1111 3
#292000
0!
b1111 "
1#
0%
1'
b1111 (
0.
b1111 2
#293000
1!
1%
1)
b00000100 *
1,
0-
1.
00
11
b1110 3
#294000
0!
b1110 "
0#
0%
0'
b1110 (
0.
b1110 2
#295000
1!
1%
0)
1.
